penguim_analyst_guy/__init__.py
penguim_analyst_guy-0.1.4.dist-info/METADATA
penguim_analyst_guy-0.1.4.dist-info/WHEEL
penguim_analyst_guy-0.1.4.dist-info/RECORD
